Workbook

Sheet Payroll Master
A1: Monthly Payroll Register
A2: Detailed payroll file for a multi-department organization
A4: Emp ID | B4: Employee Name | C4: Department | D4: Grade | E4: Basic Salary | F4: Housing | G4: Transport | H4: Overtime | I4: Bonus | J4: Gross Pay | K4: Tax | L4: Social Security | M4: Medical | N4: Other Deductions | O4: Net Pay | P4: Bank
A5: EMP-201 | B5: Mona Khalil | C5: Finance | D5: G6 | E5: 4200 | F5: 700 | G5: 280 | H5: 90 | I5: 250 | J5: =SUM(E5:I5) | K5: =J5*0.09 | L5: =J5*0.035 | M5: =45 | N5: =20 | O5: =J5-K5-L5-M5-N5 | P5: Bank Audi
A6: EMP-202 | B6: Rami Saad | C6: Operations | D6: G7 | E6: 4700 | F6: 820 | G6: 310 | H6: 140 | I6: 300 | J6: =SUM(E6:I6) | K6: =J6*0.09 | L6: =J6*0.035 | M6: =45 | N6: =20 | O6: =J6-K6-L6-M6-N6 | P6: BLOM
A7: EMP-203 | B7: Nour Haddad | C7: Sales | D7: G6 | E7: 4350 | F7: 760 | G7: 290 | H7: 180 | I7: 450 | J7: =SUM(E7:I7) | K7: =J7*0.09 | L7: =J7*0.035 | M7: =45 | N7: =20 | O7: =J7-K7-L7-M7-N7 | P7: Bank Audi
A8: EMP-204 | B8: Lina Harb | C8: Marketing | D8: G5 | E8: 3900 | F8: 680 | G8: 260 | H8: 110 | I8: 220 | J8: =SUM(E8:I8) | K8: =J8*0.09 | L8: =J8*0.035 | M8: =45 | N8: =20 | O8: =J8-K8-L8-M8-N8 | P8: Byblos
A9: EMP-205 | B9: Omar Zein | C9: IT | D9: G7 | E9: 5100 | F9: 900 | G9: 320 | H9: 120 | I9: 380 | J9: =SUM(E9:I9) | K9: =J9*0.09 | L9: =J9*0.035 | M9: =45 | N9: =20 | O9: =J9-K9-L9-M9-N9 | P9: BLOM
A10: EMP-206 | B10: Dana Fares | C10: HR | D10: G5 | E10: 3850 | F10: 650 | G10: 250 | H10: 75 | I10: 180 | J10: =SUM(E10:I10) | K10: =J10*0.09 | L10: =J10*0.035 | M10: =45 | N10: =20 | O10: =J10-K10-L10-M10-N10 | P10: BankMed
A11: EMP-207 | B11: Fadi Nasser | C11: Procurement | D11: G6 | E11: 4100 | F11: 720 | G11: 280 | H11: 95 | I11: 200 | J11: =SUM(E11:I11) | K11: =J11*0.09 | L11: =J11*0.035 | M11: =45 | N11: =20 | O11: =J11-K11-L11-M11-N11 | P11: Byblos
A12: EMP-208 | B12: Maya Tannous | C12: Logistics | D12: G5 | E12: 3720 | F12: 640 | G12: 240 | H12: 130 | I12: 160 | J12: =SUM(E12:I12) | K12: =J12*0.09 | L12: =J12*0.035 | M12: =45 | N12: =20 | O12: =J12-K12-L12-M12-N12 | P12: BankMed
A13: EMP-209 | B13: Karim Abboud | C13: Legal | D13: G7 | E13: 5200 | F13: 940 | G13: 330 | H13: 40 | I13: 500 | J13: =SUM(E13:I13) | K13: =J13*0.09 | L13: =J13*0.035 | M13: =45 | N13: =20 | O13: =J13-K13-L13-M13-N13 | P13: Bank Audi
A14: EMP-210 | B14: Rita Ghosn | C14: Facilities | D14: G4 | E14: 3400 | F14: 580 | G14: 220 | H14: 85 | I14: 120 | J14: =SUM(E14:I14) | K14: =J14*0.09 | L14: =J14*0.035 | M14: =45 | N14: =20 | O14: =J14-K14-L14-M14-N14 | P14: BLC
A15: EMP-211 | B15: Ziad Moussa | C15: Operations | D15: G6 | E15: 4450 | F15: 770 | G15: 290 | H15: 150 | I15: 260 | J15: =SUM(E15:I15) | K15: =J15*0.09 | L15: =J15*0.035 | M15: =45 | N15: =20 | O15: =J15-K15-L15-M15-N15 | P15: BLC
A16: EMP-212 | B16: Hiba Daher | C16: Sales | D16: G5 | E16: 3980 | F16: 690 | G16: 255 | H16: 170 | I16: 340 | J16: =SUM(E16:I16) | K16: =J16*0.09 | L16: =J16*0.035 | M16: =45 | N16: =20 | O16: =J16-K16-L16-M16-N16 | P16: BLOM
... A24: EMP-220 | B24: Mira Chahine | C24: Legal | D24: G6 | E24: 4550 | F24: 800 | G24: 295 | H24: 50 | I24: 260 | J24: =SUM(E24:I24) | K24: =J24*0.09 | L24: =J24*0.035 | M24: =45 | N24: =20 | O24: =J24-K24-L24-M24-N24 | P24: Bank Audi

Sheet Department Summary
A1: Payroll by Department
A2: Department-level payroll cost summary
A4: Department | B4: Headcount | C4: Gross Payroll | D4: Net Payroll
A5: Finance | B5: =COUNTIF('Payroll Master'!C5:C24,A5) | C5: =SUMIF('Payroll Master'!C5:C24,A5,'Payroll Master'!J5:J24) | D5: =SUMIF('Payroll Master'!C5:C24,A5,'Payroll Master'!O5:O24)
A6: Operations | B6: =COUNTIF('Payroll Master'!C5:C24,A6) | C6: =SUMIF('Payroll Master'!C5:C24,A6,'Payroll Master'!J5:J24) | D6: =SUMIF('Payroll Master'!C5:C24,A6,'Payroll Master'!O5:O24)
A7: Sales | B7: =COUNTIF('Payroll Master'!C5:C24,A7) | C7: =SUMIF('Payroll Master'!C5:C24,A7,'Payroll Master'!J5:J24) | D7: =SUMIF('Payroll Master'!C5:C24,A7,'Payroll Master'!O5:O24)
A8: Marketing | B8: =COUNTIF('Payroll Master'!C5:C24,A8) | C8: =SUMIF('Payroll Master'!C5:C24,A8,'Payroll Master'!J5:J24) | D8: =SUMIF('Payroll Master'!C5:C24,A8,'Payroll Master'!O5:O24)
A9: IT | B9: =COUNTIF('Payroll Master'!C5:C24,A9) | C9: =SUMIF('Payroll Master'!C5:C24,A9,'Payroll Master'!J5:J24) | D9: =SUMIF('Payroll Master'!C5:C24,A9,'Payroll Master'!O5:O24)
A10: HR | B10: =COUNTIF('Payroll Master'!C5:C24,A10) | C10: =SUMIF('Payroll Master'!C5:C24,A10,'Payroll Master'!J5:J24) | D10: =SUMIF('Payroll Master'!C5:C24,A10,'Payroll Master'!O5:O24)
A11: Procurement | B11: =COUNTIF('Payroll Master'!C5:C24,A11) | C11: =SUMIF('Payroll Master'!C5:C24,A11,'Payroll Master'!J5:J24) | D11: =SUMIF('Payroll Master'!C5:C24,A11,'Payroll Master'!O5:O24)
A12: Logistics | B12: =COUNTIF('Payroll Master'!C5:C24,A12) | C12: =SUMIF('Payroll Master'!C5:C24,A12,'Payroll Master'!J5:J24) | D12: =SUMIF('Payroll Master'!C5:C24,A12,'Payroll Master'!O5:O24)
A13: Legal | B13: =COUNTIF('Payroll Master'!C5:C24,A13) | C13: =SUMIF('Payroll Master'!C5:C24,A13,'Payroll Master'!J5:J24) | D13: =SUMIF('Payroll Master'!C5:C24,A13,'Payroll Master'!O5:O24)
A14: Facilities | B14: =COUNTIF('Payroll Master'!C5:C24,A14) | C14: =SUMIF('Payroll Master'!C5:C24,A14,'Payroll Master'!J5:J24) | D14: =SUMIF('Payroll Master'!C5:C24,A14,'Payroll Master'!O5:O24)
